envg/__init__.py
envg/default.py
envg/main.py
envg/misc.py
envg/osrelease.py
envg/secrets.py
envg/system.py
envg-0.0.10.dist-info/LICENSE
envg-0.0.10.dist-info/METADATA
envg-0.0.10.dist-info/WHEEL
envg-0.0.10.dist-info/top_level.txt
envg-0.0.10.dist-info/RECORD
