Metadata-Version: 2.1
Name: envg
Version: 0.0.10
Summary: Environment varriables as globals
Author-email: José Antonio Puértolas Montañés <63794670+j5pu@users.noreply.github.com>
License: MIT
Project-URL: Homepage, https://github.com/j5pu/envg
Requires-Python: >=3.11
License-File: LICENSE
Requires-Dist: nodeps
Provides-Extra: dev
Requires-Dist: pproj[all] ; extra == 'dev'
